<Properties StartupConfiguration="{DB1FEA45-F47D-9CD1-1FFB-EC5522D71287}|">
  <MonoDevelop.Ide.Workbench ActiveDocument="Assets/MyAudioController.cs">
    <Files>
      <File FileName="Assets/Scripts/GameController.cs" Line="10" Column="11" />
      <File FileName="Assets/Scripts/MoneyController.cs" Line="61" Column="66" />
      <File FileName="Assets/StartButtonController.cs" Line="40" Column="29" />
      <File FileName="Assets/Scripts/KeyEventController.cs" Line="59" Column="74" />
      <File FileName="Assets/HaltButtonController.cs" Line="41" Column="6" />
      <File FileName="Assets/MyAudioController.cs" Line="20" Column="36" />
    </Files>
    <Pads>
      <Pad Id="ProjectPad">
        <State name="__root__">
          <Node name="CentralProcessingUnit" expanded="True">
            <Node name="Assets" expanded="True">
              <Node name="BuildScripts" expanded="True" />
              <Node name="Interfaces" expanded="True" />
              <Node name="Scripts" expanded="True" />
              <Node name="MyAudioController.cs" selected="True" />
            </Node>
          </Node>
        </State>
      </Pad>
    </Pads>
  </MonoDevelop.Ide.Workbench>
  <MonoDevelop.Ide.DebuggingService.PinnedWatches />
  <MonoDevelop.Ide.Workspace ActiveConfiguration="Debug" />
  <MonoDevelop.Ide.ItemProperties.Assembly-CSharp PreferredExecutionTarget="92fe9ee4-47e7-4b12-ac93-01f20abef44f" />
  <MonoDevelop.Ide.DebuggingService.Breakpoints>
    <BreakpointStore />
  </MonoDevelop.Ide.DebuggingService.Breakpoints>
  <MultiItemStartupConfigurations />
</Properties>